hbsearch.py
hbsearch-0.1.2.dist-info/METADATA
hbsearch-0.1.2.dist-info/WHEEL
hbsearch-0.1.2.dist-info/top_level.txt
hbsearch-0.1.2.dist-info/RECORD
