Metadata-Version: 2.1
Name: hbsearch
Version: 0.1.2
Summary: Various BM25 algorithms for document ranking
Author: Seth
Author-email: ssyaigo@gmail.com
Requires-Dist: FlagEmbedding ==1.2.11
Requires-Dist: rank-bm25 ==0.2.2
Requires-Dist: jieba
